kata04/__init__.py
kata04/converter_service.py
kata04/field.py
paquetekata04/__init__.py
paquetekata04/converter_service.py
paquetekata04/field.py
kata04-1.0.2.dist-info/METADATA
kata04-1.0.2.dist-info/WHEEL
kata04-1.0.2.dist-info/top_level.txt
kata04-1.0.2.dist-info/RECORD
