Metadata-Version: 2.1
Name: kata04
Version: 1.0.2
Author: Jose Joaquin Sol
